ectrans4py/__init__.py
ectrans4py/bin/ectrans
ectrans4py/bin/ectrans-benchmark-cpu-dp
ectrans4py/bin/ectrans-lam-benchmark-cpu-dp
ectrans4py/include/ectrans/dir_trans_dp.h
ectrans4py/include/ectrans/dir_transad_dp.h
ectrans4py/include/ectrans/dist_grid_32_dp.h
ectrans4py/include/ectrans/dist_grid_dp.h
ectrans4py/include/ectrans/dist_spec_dp.h
ectrans4py/include/ectrans/edir_trans_dp.h
ectrans4py/include/ectrans/edir_transad_dp.h
ectrans4py/include/ectrans/edist_grid_dp.h
ectrans4py/include/ectrans/edist_spec_dp.h
ectrans4py/include/ectrans/egath_grid_dp.h
ectrans4py/include/ectrans/egath_spec_dp.h
ectrans4py/include/ectrans/egpnorm_trans_dp.h
ectrans4py/include/ectrans/einv_trans_dp.h
ectrans4py/include/ectrans/einv_transad_dp.h
ectrans4py/include/ectrans/esetup_trans_dp.h
ectrans4py/include/ectrans/especnorm_dp.h
ectrans4py/include/ectrans/etibihie_dp.h
ectrans4py/include/ectrans/etrans_end_dp.h
ectrans4py/include/ectrans/etrans_inq_dp.h
ectrans4py/include/ectrans/etrans_release_dp.h
ectrans4py/include/ectrans/fpbipere_dp.h
ectrans4py/include/ectrans/gath_grid_32_dp.h
ectrans4py/include/ectrans/gath_grid_dp.h
ectrans4py/include/ectrans/gath_spec_dp.h
ectrans4py/include/ectrans/get_current.h
ectrans4py/include/ectrans/gpnorm_trans_dp.h
ectrans4py/include/ectrans/gpnorm_transad_dp.h
ectrans4py/include/ectrans/gpnorm_transtl_dp.h
ectrans4py/include/ectrans/horiz_field_dp.h
ectrans4py/include/ectrans/ini_spec_dist.h
ectrans4py/include/ectrans/inv_trans_dp.h
ectrans4py/include/ectrans/inv_transad_dp.h
ectrans4py/include/ectrans/setup_trans0.h
ectrans4py/include/ectrans/setup_trans_dp.h
ectrans4py/include/ectrans/specnorm_dp.h
ectrans4py/include/ectrans/trans_end_dp.h
ectrans4py/include/ectrans/trans_inq_dp.h
ectrans4py/include/ectrans/trans_pnm_dp.h
ectrans4py/include/ectrans/trans_release_dp.h
ectrans4py/include/ectrans/transi.h
ectrans4py/include/ectrans/version.h
ectrans4py/include/ectrans/vordiv_to_uv_dp.h
ectrans4py-1.6.0.dist-info/METADATA
ectrans4py-1.6.0.dist-info/WHEEL
ectrans4py-1.6.0.dist-info/top_level.txt
ectrans4py-1.6.0.dist-info/RECORD
ectrans4py-1.6.0.dist-info/licenses/AUTHORS
ectrans4py-1.6.0.dist-info/licenses/LICENSE
