Metadata-Version: 2.4
Name: ectrans4py
Version: 1.6.0
Summary: ECTRANS interface for Python
Classifier: Development Status :: 3 - Alpha
Classifier: Intended Audience :: Science/Research
Classifier: Programming Language :: Python
Classifier: Programming Language :: Python :: 3.10
Classifier: Programming Language :: Python :: 3.11
Classifier: Programming Language :: Python :: 3.12
Classifier: Operating System :: Unix
Requires-Python: >=3.10
License-File: LICENSE
License-File: AUTHORS
Requires-Dist: numpy
Requires-Dist: ctypesForFortran<2.0.0
Dynamic: license-file
